MANIFEST.in
README.md
setup.py
examples/Ice_200K.RI
examples/README.md
examples/Water_300K_Raman_Castner.dat
examples/eps_omega_water_300K_TTM3F.dat
examples/water_300.RI
examples/water_full_Siegelstein.RI
spectrumfitter/__init__.py
spectrumfitter/spectralmodel.py
spectrumfitter/spectrumfitter.py
spectrumfitter.egg-info/PKG-INFO
spectrumfitter.egg-info/SOURCES.txt
spectrumfitter.egg-info/dependency_links.txt
spectrumfitter.egg-info/not-zip-safe
spectrumfitter.egg-info/requires.txt
spectrumfitter.egg-info/top_level.txt