Metadata-Version: 1.1
Name: spectrumfitter
Version: 0.1.0
Summary: basic utility for fitting dielectric spectra
Home-page: https://github.com/delton137/spectrumfitter
Author: Daniel C Elton
Author-email: delton17@gmail.com
License: MIT
Download-URL: https://github.com/delton137/spectrumfitter/archive/master.zip
Platform: UNKNOWN
Classifier: Topic :: Scientific/Engineering :: Physics
Classifier: License :: OSI Approved :: MIT License
Classifier: Programming Language :: Python :: 2.7
Classifier: Intended Audience :: Science/Research
